GDV_feature_shows/__init__.py
GDV_feature_shows/api_client.py
GDV_feature_shows/excel_forming_logic.py
GDV_feature_shows/feature_extraction.py
GDV_feature_shows/interface_gradio.py
GDV_feature_shows/main.py
GDV_feature_shows/name_volume.py
GDV_feature_shows/parsing.py
GDV_feature_shows/process.py
GDV_feature_shows/resource_manager.py
GDV_feature_shows/settings_handler.py
GDV_feature_shows-0.2.5.dist-info/METADATA
GDV_feature_shows-0.2.5.dist-info/WHEEL
GDV_feature_shows-0.2.5.dist-info/entry_points.txt
GDV_feature_shows-0.2.5.dist-info/top_level.txt
GDV_feature_shows-0.2.5.dist-info/RECORD
